tgcrypto.cpython-313-aarch64-linux-musl.so
tests/__init__.py
tests/cbc/test_cbc.py
tests/cbc/__init__.py
tests/ige/test_ige.py
tests/ige/__init__.py
tests/ctr/test_ctr.py
tests/ctr/__init__.py
stefano_tgcrypto-1.2.7.dist-info/WHEEL
stefano_tgcrypto-1.2.7.dist-info/top_level.txt
stefano_tgcrypto-1.2.7.dist-info/METADATA
stefano_tgcrypto-1.2.7.dist-info/RECORD
stefano_tgcrypto-1.2.7.dist-info/licenses/NOTICE
stefano_tgcrypto-1.2.7.dist-info/licenses/COPYING.lesser
stefano_tgcrypto-1.2.7.dist-info/licenses/COPYING
